cloud_run_flask_template/__init__.py
cloud_run_flask_template/generator.py
cloud_run_flask_template-0.4.dist-info/LICENSE
cloud_run_flask_template-0.4.dist-info/METADATA
cloud_run_flask_template-0.4.dist-info/WHEEL
cloud_run_flask_template-0.4.dist-info/entry_points.txt
cloud_run_flask_template-0.4.dist-info/top_level.txt
cloud_run_flask_template-0.4.dist-info/RECORD
