Metadata-Version: 2.1
Name: cloud-run-flask-template
Version: 0.4
Summary: A template for Google Cloud Run Flask development
Home-page: https://github.com/Yash-Kavaiya/gcloudrun-flaskpython
Author: Yash Kavaiya
Author-email: yash.kavaiya3@gmail.com
Classifier: Programming Language :: Python :: 3
Classifier: License :: OSI Approved :: MIT License
Classifier: Operating System :: OS Independent
License-File: LICENSE
Requires-Dist: Flask ==3.0.3
Requires-Dist: gunicorn ==22.0.0
Requires-Dist: Werkzeug ==3.0.3
